Metadata-Version: 2.1
Name: wincom
Version: 0.0.2
Summary: Python module for writing websites.Two It 2022 (two-it.netlify.app API wrapper)
Home-page: https://github.com/TwoIt202/wincom
Download-URL: https://github.com/TwoIt202/wincom/raw/1faa18d7f387f20309a0ecab37db79ad8d161df8/wincom.zip
Author: two-it2022
Author-email: kodland.group@gmail.com
License: Apache License, Version 0.2, see LICENSE file
Classifier: License :: OSI Approved :: Apache Software License
Classifier: Operating System :: OS Independent
Classifier: Intended Audience :: End Users/Desktop
Classifier: Intended Audience :: Developers
Classifier: Programming Language :: Python
Classifier: Programming Language :: Python :: 3
Classifier: Programming Language :: Python :: 3.6
Classifier: Programming Language :: Python :: 3.7
Classifier: Programming Language :: Python :: 3.8
Classifier: Programming Language :: Python :: Implementation :: PyPy
Classifier: Programming Language :: Python :: Implementation :: CPython
